pipelineservice/__init__.py
pipelineservice/kernel_approximation.py
pipelineservice/pipeline.py
pipelineservice/compose/__init__.py
pipelineservice/compose/_column_transformer.py
pipelineservice/decomposition/__init__.py
pipelineservice/decomposition/_decomposition.py
pipelineservice/discretisation/__init__.py
pipelineservice/discretisation/_discretisation.py
pipelineservice/explain/__init__.py
pipelineservice/explain/_explain.py
pipelineservice/feature_selection/__init__.py
pipelineservice/feature_selection/_from_model.py
pipelineservice/feature_selection/_sequential.py
pipelineservice/impute/__init__.py
pipelineservice/impute/_base.py
pipelineservice/neighbors/__init__.py
pipelineservice/neighbors/_neighbors.py
pipelineservice/outlier/__init__.py
pipelineservice/outlier/_outlier.py
pipelineservice/preprocessing/__init__.py
pipelineservice/preprocessing/_data.py
pipelineservice/preprocessing/_discretization.py
pipelineservice/tf/__init__.py
pipelineservice/tf/tabnet.py
pipelineservice/tf/tabular_combiner.py
pipelineservice-1.3.2.dist-info/LICENSE
pipelineservice-1.3.2.dist-info/METADATA
pipelineservice-1.3.2.dist-info/WHEEL
pipelineservice-1.3.2.dist-info/top_level.txt
pipelineservice-1.3.2.dist-info/RECORD
