Metadata-Version: 2.1
Name: pipelineservice
Version: 1.3.2
Summary: Auto machine learning, deep learning library in Python.
Home-page: https://github.com/toandaominh1997/pipelineservice
Author: toandaominh1997
Author-email: toandaominh1997@gmail.com
License: MIT
Platform: UNKNOWN
Classifier: License :: OSI Approved :: MIT License
Classifier: Programming Language :: Python :: 3.7
Classifier: Programming Language :: Python :: 3.8
License-File: LICENSE
Requires-Dist: numpy
Requires-Dist: pandas
Requires-Dist: scikit-learn
Requires-Dist: transformers
